setup.py
plaid-stubs/__init__.pyi
plaid-stubs/client.pyi
plaid-stubs/errors.pyi
plaid-stubs/requester.pyi
plaid-stubs/utils.pyi
plaid-stubs/version.pyi
plaid-stubs/api/__init__.pyi
plaid-stubs/api/accounts.pyi
plaid-stubs/api/api.pyi
plaid-stubs/api/assets.pyi
plaid-stubs/api/auth.pyi
plaid-stubs/api/categories.pyi
plaid-stubs/api/credit_details.pyi
plaid-stubs/api/holdings.pyi
plaid-stubs/api/identity.pyi
plaid-stubs/api/income.pyi
plaid-stubs/api/institutions.pyi
plaid-stubs/api/investment_transactions.pyi
plaid-stubs/api/item.pyi
plaid-stubs/api/liabilities.pyi
plaid-stubs/api/link_token.pyi
plaid-stubs/api/processor.pyi
plaid-stubs/api/sandbox.pyi
plaid-stubs/api/transactions.pyi
plaid_stubs.egg-info/PKG-INFO
plaid_stubs.egg-info/SOURCES.txt
plaid_stubs.egg-info/dependency_links.txt
plaid_stubs.egg-info/requires.txt
plaid_stubs.egg-info/top_level.txt