Metadata-Version: 2.1
Name: plaid-stubs
Version: 0.3
Summary: Plaid stubs
Home-page: https://github.com/monarchmoney/plaid-stubs
License: MIT License
Platform: UNKNOWN
Classifier: Development Status :: 3 - Alpha
Classifier: Programming Language :: Python :: 3
Classifier: Programming Language :: Python :: 3.7
